[
  {
    "key": "greenshop-amsterdam",
    "roles": [
      "InventorySupply",
      "ProductDistribution"
    ],
    "name": {
      "en": "GreenShop Store Amsterdam"
    },
    "custom": {
      "type": {
        "key": "physicalStore"
      },
      "fields": {
        "openingTimes": {
          "en": "Mo-Fr. 9:00AM - 7:00PM\nSa. 10:00AM - 7:00PM"
        },
        "imageUrl": ""
      }
    },
    "address": {
      "streetName": "Van Boshuizenstraat",
      "streetNumber": "128",
      "postalCode": "1082 AN",
      "city": "Amsterdam",
      "country": "NL"
    },
    "geoLocation": {
      "coordinates": [
        52.324768,
        4.886341
      ],
      "type": "Point"
    }
  },
  {
    "key": "greenshop-store-salzburg",
    "roles": [
      "InventorySupply",
      "ProductDistribution"
    ],
    "name": {
      "en": "GreenShop Store Salzburg"
    },
    "custom": {
      "type": {
        "key": "physicalStore"
      },
      "fields": {
        "openingTimes": {
          "en": "Mo-Fr. 11:00AM - 7:30PM\nSa. 10:00AM - 6:30PM"
        },
        "imageUrl": ""
      }
    },
    "address": {
      "streetName": "Bayerhamerstrasse",
      "streetNumber": "35",
      "postalCode": "8342",
      "city": "Salzburg",
      "country": "AT"
    },
    "geoLocation": {
      "coordinates": [
        47.81102160096723,
        13.050144918747083
      ],
      "type": "Point"
    }
  },
  {
    "key": "greenshop-store-berlin",
    "roles": [
      "InventorySupply",
      "ProductDistribution"
    ],
    "name": {
      "en": "GreenShop Store Berlin"
    },
    "custom": {
      "type": {
        "key": "physicalStore"
      },
      "fields": {
        "openingTimes": {
          "en": "Mo-Fr. 9:00AM - 7:30PM\nSa. 10:30AM - 5:00PM"
        },
        "imageUrl": ""
      }
    },
    "address": {
      "streetName": "Brandenburgische Straße",
      "streetNumber": "16",
      "postalCode": "10997",
      "city": "Berlin",
      "country": "DE"
    },
    "geoLocation": {
      "coordinates": [
        52.49446560404963,
        13.309785655098567
      ],
      "type": "Point"
    }
  }
]
